fortytwocli/__init__.py
fortytwocli/api.py
fortytwocli/authorize.py
fortytwocli/const.py
fortytwocli/exception.py
fortytwocli/init.py
fortytwocli/ipCalc.py
fortytwocli/main.py
fortytwocli/project.py
fortytwocli/status.py
fortytwocli/util.py
fortytwocli-0.2.1.dist-info/entry_points.txt
fortytwocli-0.2.1.dist-info/LICENSE
fortytwocli-0.2.1.dist-info/WHEEL
fortytwocli-0.2.1.dist-info/METADATA
fortytwocli-0.2.1.dist-info/RECORD
