Metadata-Version: 2.1
Name: fortytwocli
Version: 0.2.1
Summary: command line tool for 42 intra.
Home-page: https://github.com/dhaiibfiukkiu/42cli
License: MIT
Author: Hibiki Okada
Author-email: hokada@student.42tokyo.jp
Requires-Python: >=3.8,<4.0
Classifier: License :: OSI Approved :: MIT License
Classifier: Programming Language :: Python :: 3
Classifier: Programming Language :: Python :: 3.8
Requires-Dist: GitPython (>=3.1.3,<4.0.0)
Requires-Dist: click (>=7.1.2,<8.0.0)
Requires-Dist: halo (>=0.0.29,<0.0.30)
Requires-Dist: inquirer (>=2.6.3,<3.0.0)
Requires-Dist: rich (>=6.0.0,<7.0.0)
Project-URL: Repository, https://github.com/dhaiibfiukkiu/42cli
